webdriverutils.py
d_utils-0.0.9.dist-info/LICENSE.txt
d_utils-0.0.9.dist-info/METADATA
d_utils-0.0.9.dist-info/WHEEL
d_utils-0.0.9.dist-info/top_level.txt
d_utils-0.0.9.dist-info/RECORD
