Metadata-Version: 2.1
Name: d-utils
Version: 0.0.9
Summary: Utilities for Web Scraping
Home-page: UNKNOWN
Author: Veldhaenchen
Author-email: johannes.velde@gmx.de
License: UNKNOWN
Platform: UNKNOWN
Classifier: Programming Language :: Python :: 3
Classifier: Programming Language :: Python :: 3.6
Classifier: Programming Language :: Python :: 3.7
Classifier: License :: OSI Approved :: GNU General Public License v2 or later (GPLv2+)
Classifier: Operating System :: OS Independent
Requires-Dist: selenium
Requires-Dist: pyvirtualdisplay
Requires-Dist: webdriverdownloader
Provides-Extra: dev
Requires-Dist: pytest (>=3.7) ; extra == 'dev'
